karrio/mappers/dhl_universal/__init__.py
karrio/mappers/dhl_universal/mapper.py
karrio/mappers/dhl_universal/proxy.py
karrio/mappers/dhl_universal/settings.py
karrio/plugins/dhl_universal/__init__.py
karrio/providers/dhl_universal/__init__.py
karrio/providers/dhl_universal/error.py
karrio/providers/dhl_universal/tracking.py
karrio/providers/dhl_universal/units.py
karrio/providers/dhl_universal/utils.py
karrio/schemas/dhl_universal/__init__.py
karrio/schemas/dhl_universal/tracking.py
karrio_dhl_universal-2026.1.4.dist-info/METADATA
karrio_dhl_universal-2026.1.4.dist-info/WHEEL
karrio_dhl_universal-2026.1.4.dist-info/entry_points.txt
karrio_dhl_universal-2026.1.4.dist-info/top_level.txt
karrio_dhl_universal-2026.1.4.dist-info/RECORD
